pb_encoding/__init__.py
pb_encoding/decoder.py
pb_encoding/encoder.py
pb_encoding/typing.py
pb_encoding-0.4.0.dist-info/METADATA
pb_encoding-0.4.0.dist-info/WHEEL
pb_encoding-0.4.0.dist-info/licenses/LICENSE
pb_encoding-0.4.0.dist-info/licenses/LICENSE_origin
pb_encoding-0.4.0.dist-info/RECORD
