Metadata-Version: 2.1
Name: pb_encoding
Version: 0.4.0
Summary: Some encode/decode functions extracted from google.protobuf
Project-URL: homepage, https://github.com/Grvzard/pb_encoding
License-File: LICENSE
License-File: LICENSE_origin
Classifier: License :: OSI Approved :: Apache Software License
Classifier: Programming Language :: Python :: 3
Requires-Python: >=3.8
Provides-Extra: dev
Requires-Dist: pytest; extra == 'dev'
